pythra-0.1.19.dist-info/WHEEL
pythra-0.1.19.dist-info/entry_points.txt
pythra-0.1.19.dist-info/top_level.txt
pythra-0.1.19.dist-info/METADATA
pythra-0.1.19.dist-info/RECORD
pythra-0.1.19.dist-info/licenses/LICENSE
pythra/generate_icons.py
pythra/test.py
pythra/reconciler_cython.pyx
pythra/reconciler.py
pythra/styles.py
pythra/server.py
pythra/theme.py
pythra/drawing.py
pythra/package_registry.py
pythra/widgets_more.py
pythra/widgets.py
pythra/package_security.py
pythra/state.py
pythra/font_encoder.py
pythra/events.py
pythra/reconciler_cython.c
pythra/reconciler_loader.py
pythra/package_manager.py
pythra/plugins.py
pythra/painting.py
pythra/api.py
pythra/core.py
pythra/debug_utils.py
pythra/package_system.py
pythra/navigation.py
pythra/controllers.py
pythra/config.py
pythra/reconciler_cython.cpython-39-x86_64-linux-gnu.so
pythra/__init__.py
pythra/reconciler_cython.cp313-win_amd64.pyd
pythra/class_list.py
pythra/rust_reconciler_adapter.py
pythra/id_manager.py
pythra/base.py
pythra/icons/icons_outlined_1.py
pythra/icons/icons_sharp.py
pythra/icons/icons_rounded.py
pythra/icons/icons_rounded_1.py
pythra/icons/icons_outlined.py
pythra/icons/icons_sharp_1.py
pythra/icons/__init__.py
pythra/icons/base.py
pythra/utils/__init__.py
pythra/cli/main.py
pythra/cli/package_commands.py
pythra/cli/__init__.py
pythra/derived_widgets/dropdown/style.py
pythra/derived_widgets/dropdown/controller.py
pythra/derived_widgets/dropdown/dropdown.py
pythra/derived_widgets/dropdown/__init__.py
pythra/window/window_manager.py
pythra/window/max.py
pythra/window/main.py
pythra/window/__init__.py
pythra/window/webwidget.py
pythra/tests/__init__.py
pythra/tests/test_rust_adapter.py
pythra/pythra_cli/main.py
pythra/pythra_cli/package_commands.py
pythra/pythra_cli/__init__.py
perv_tests/main_bottomNavBar_pageChang.py
perv_tests/main_grid_scaffold_appbar_test.py
perv_tests/main_drawer_simple.py
perv_tests/main_grid_test.py
perv_tests/state_test.py
perv_tests/main.py
perv_tests/main_bottom_sheet_snack_bar.py
perv_tests/main_grid_a.py
project_template/__init__.py
project_template/lib/main.py
project_template/lib/__init__.py
