Metadata-Version: 2.4
Name: pythra
Version: 0.1.19
Summary: PyThra — a Flutter-like GUI framework in Python. a declarative Python UI framework for desktop apps with a webview renderer.
Author-email: Ahmad Muhammad Bashir <ambashir02@gmail.com>
License: MIT
Classifier: Programming Language :: Python :: 3
Classifier: License :: OSI Approved :: MIT License
Classifier: Operating System :: OS Independent
Requires-Python: >=3.9
License-File: LICENSE
Requires-Dist: PySide6>=6.10.0
Requires-Dist: pyyaml>=6.0
Requires-Dist: setuptools>=65.0
Requires-Dist: orjson>=3.11.4
Requires-Dist: typer>=0.12.0
Requires-Dist: rich>=13.0.0
Requires-Dist: click>=8.0.0
Requires-Dist: tabulate>=0.8.0
Requires-Dist: PyYAML>=5.4.0
Requires-Dist: pyinstaller>=4.0
Requires-Dist: semver>=3.0.0
Requires-Dist: requests>=2.31.0
Requires-Dist: Cython>=0.29.30
Requires-Dist: dbus-python; sys_platform == "linux"
Dynamic: license-file
